perch/__init__.py
perch/main.py
perch/settings.py
perch/version.py
perch-0.0.9.dist-info/LICENSE
perch-0.0.9.dist-info/METADATA
perch-0.0.9.dist-info/WHEEL
perch-0.0.9.dist-info/entry_points.txt
perch-0.0.9.dist-info/top_level.txt
perch-0.0.9.dist-info/RECORD
